markit_rs_recorder/__init__.py
markit_rs_recorder/__main__.py
markit_rs_recorder/cmd/__init__.py
markit_rs_recorder/cmd/calibrate.py
markit_rs_recorder/cmd/post_process.py
markit_rs_recorder/cmd/serve.py
markit_rs_recorder/common/__init__.py
markit_rs_recorder/common/config.py
markit_rs_recorder/common/interaction.py
markit_rs_recorder/common/record.py
markit_rs_recorder/common/utils.py
markit_rs_recorder/filters/__init__.py
markit_rs_recorder/io/Compression.py
markit_rs_recorder/io/DirectoryReader.py
markit_rs_recorder/io/Sequence.py
markit_rs_recorder/io/Sync.py
markit_rs_recorder/io/__init__.py
markit_rs_recorder/scripts/__init__.py
markit_rs_recorder/scripts/configure.py
markit_rs_recorder-2.0.0.dist-info/METADATA
markit_rs_recorder-2.0.0.dist-info/WHEEL
markit_rs_recorder-2.0.0.dist-info/top_level.txt
markit_rs_recorder-2.0.0.dist-info/RECORD
